my_package/__init__.py
my_package/example.py
for_pdp_by_jasurbek-0.1.dist-info/METADATA
for_pdp_by_jasurbek-0.1.dist-info/WHEEL
for_pdp_by_jasurbek-0.1.dist-info/top_level.txt
for_pdp_by_jasurbek-0.1.dist-info/RECORD
