Metadata-Version: 2.4
Name: for_PDP_by_Jasurbek
Version: 0.1
Summary: For PDP lesson
Author: Jasurbek
Author-email: olimjonovzilxa@gmail.com
License: MIT
Requires-Python: >=3.6
Dynamic: author
Dynamic: author-email
Dynamic: description
Dynamic: license
Dynamic: requires-python
Dynamic: summary
